{
    "img": null,
    "title": "В каком случае разрешается эксплуатация транспортного средства?",
    "answers": [
        "1.                        Загрязнены внешние световые приборы",
        "2.                        Регулировка фар не соответствует установленным требованиям",
        "3.                        На световых приборах используются рассеиватели и лампы, не соответствующие типу данного светового прибора",
        "4.                        На транспортном средстве спереди установлены световые приборы с огнями оранжевого цвета"
    ],
    "correct_answer_index": "4",
    "full_corrent_answer": "\nПравильный ответ: 4\n\n            Третий раздел «Внешние световые приборы» «Перечня неисправностей» запрещает эксплуатацию транспортных средств в случаях, если загрязнены внешние световые приборы (пункт 3.3), регулировка фар не соответствует установленным требованиям (пункт 3.2), на световых приборах используются рассеиватели и лампы, не соответствующие типу данного светового прибора (пункт 3.4). Этим перечнем разрешается эксплуатация ТС, на котором спереди установлены световые приборы с огнями оранжевого цвета (пункт 3.6).\n(«Перечень неисправностей», пункты 3.2, 3.3, 3.4, 3.6)        "
}