{
    "img": null,
    "title": "Водитель обгоняемого транспортного средства:",
    "answers": [
        "1.                        Обязан снизить скорость движения",
        "2.                        Обязан не повышать скорость движения",
        "3.                        Имеет право действовать по своему усмотрению"
    ],
    "correct_answer_index": "2",
    "full_corrent_answer": "\nПравильный ответ: 2\n\n            Водителю обгоняемого транспортного средства запрещается препятствовать обгону повышением скорости движения или иными действиями.\n(Пункт 11.3 ПДД)        "
}