{
    "img": "https://s.drom.ru/i24227/pdd/tickets/2016/1542609019.jpg",
    "title": "Если реверсивные светофоры выключились, Вам следует:",
    "answers": [
        "1.                        Немедленно перестроиться вправо на соседнюю полосу",
        "2.                        Продолжить движение по полосе только до перекрестка",
        "3.                        При отсутствии встречных транспортных средств продолжить движение по полосе"
    ],
    "correct_answer_index": "1",
    "full_corrent_answer": "\nПравильный ответ: 1\n\n            При выключенных сигналах реверсивного светофора, который расположен над полосой, обозначенной с обеих сторон разметкой 1.9, въезд на эту полосу запрещён. Вам необходимо перестроиться на правую полосу.\n(Пункт 6.7 ПДД, «Горизонтальная разметка»)        "
}