{
    "img": null,
    "title": "Запрещается выполнять обгон транспортного средства, имеющего нанесенные на наружные поверхности специальные цветографические схемы:",
    "answers": [
        "1.                        Только при включении на нем специального звукового сигнала",
        "2.                        Только при включении на нем проблесковых маячков синего (синего и красного) цвета",
        "3.                        При наличии обоих перечисленных условий"
    ],
    "correct_answer_index": "3",
    "full_corrent_answer": "\nПравильный ответ: 3\n\n            Обязательными условиями запрещения обгона «оперативника» (и сопровождаемых им Т. С.) являются: 1 – нанесённые на наружные поверхности специальные цветографические схемы; 2 – включение на нём проблесковых маячков синего цвета или синего и красного; 3 – включение сигнального звукового сигнала.\nПравильный ответ - при наличии всех условий.\n(Пункт 3.2 ПДД)        "
}