{
    "img": null,
    "title": "В каких из перечисленных случаев разрешается движение в населенных пунктах со скоростью не более 20 км/час?",
    "answers": [
        "1.                        При движении в жилых зонах и на дворовых территориях",
        "2.                        При движении в велосипедных зонах",
        "3.                        В обоих"
    ],
    "correct_answer_index": "3",
    "full_corrent_answer": "\nПравильный ответ: 3\n\n            В обоих из перечисленных случаев разрешается движение в населенных пунктах со скоростью не более 20 км/ч.\n(Пункт 10.2 ПДД)        "
}